[
  {
    "id": "682cec216ec7634154f9acb2",
    "username": "shawnxu",
    "branch": "test1397",
    "llr": 2.227047575433337,
    "wins": 16186,
    "losses": 15896,
    "draws": 30382,
    "workers": 8,
    "sprtElo0": 0
  },
  {
    "id": "682d78a36ec7634154f9ad1f",
    "username": "Fisherman",
    "branch": "MPOverwriteFix",
    "llr": 1.7718418861471255,
    "wins": 7721,
    "losses": 7596,
    "draws": 14283,
    "workers": 6,
    "sprtElo0": -1.75
  },
  {
    "id": "682db1966ec7634154f9ad77",
    "username": "yT7Af9Fc",
    "branch": "patch-14",
    "llr": 0.7962782209442628,
    "wins": 3809,
    "losses": 3717,
    "draws": 6906,
    "workers": 6,
    "sprtElo0": 0
  },
  {
    "id": "6829fe1b6ec7634154f9a036",
    "username": "fauzi2",
    "branch": "rdtm4b",
    "llr": 0.65014028055153,
    "wins": 58765,
    "losses": 58256,
    "draws": 112347,
    "workers": 5,
    "sprtElo0": 0.5
  },
  {
    "id": "682a32aa6ec7634154f9a372",
    "username": "fauzi2",
    "branch": "rdtm4c",
    "llr": 0.6192490324373193,
    "wins": 57463,
    "losses": 56966,
    "draws": 110229,
    "workers": 11,
    "sprtElo0": 0.5
  },
  {
    "id": "682b792b6ec7634154f9aae7",
    "username": "Fisherman",
    "branch": "SortLess",
    "llr": 0.4545919337082623,
    "wins": 39858,
    "losses": 39591,
    "draws": 74599,
    "workers": 5,
    "sprtElo0": 0
  },
  {
    "id": "682d8f276ec7634154f9ad44",
    "username": "Vizvezdenec",
    "branch": "smPcTwoF11",
    "llr": 0.33774500355252923,
    "wins": 3632,
    "losses": 3582,
    "draws": 6706,
    "workers": 6,
    "sprtElo0": 0
  },
  {
    "id": "682a45b16ec7634154f9a3b3",
    "username": "shawnxu",
    "branch": "test1383",
    "llr": 0.3283028237319684,
    "wins": 45468,
    "losses": 45223,
    "draws": 85669,
    "workers": 16,
    "sprtElo0": 0
  },
  {
    "id": "682dd4906ec7634154f9adbd",
    "username": "Nonlinear",
    "branch": "next-ttmove-depth-condition",
    "llr": 0.252695645061765,
    "wins": 137,
    "losses": 114,
    "draws": 197,
    "workers": 5,
    "sprtElo0": 0
  },
  {
    "id": "682dd0cf6ec7634154f9adad",
    "username": "Nonlinear",
    "branch": "no-lower-bound-reduction",
    "llr": 0.19470112334979797,
    "wins": 782,
    "losses": 761,
    "draws": 1561,
    "workers": 6,
    "sprtElo0": 0
  },
  {
    "id": "682db1326ec7634154f9ad73",
    "username": "yT7Af9Fc",
    "branch": "patch-7-1",
    "llr": 0.13896213996352794,
    "wins": 4252,
    "losses": 4216,
    "draws": 7980,
    "workers": 7,
    "sprtElo0": 0
  },
  {
    "id": "682dd78b6ec7634154f9adc5",
    "username": "Nonlinear",
    "branch": "implicit-nmp-3",
    "llr": 0,
    "wins": 0,
    "losses": 0,
    "draws": 0,
    "workers": 0,
    "sprtElo0": 0
  },
  {
    "id": "682dd10d6ec7634154f9adb3",
    "username": "pb00067",
    "branch": "stalemateDetect",
    "llr": -0.03806022148534727,
    "wins": 49,
    "losses": 52,
    "draws": 91,
    "workers": 11,
    "sprtElo0": -1.75
  },
  {
    "id": "682dd0966ec7634154f9adab",
    "username": "Nonlinear",
    "branch": "no-lower-bound-reduction",
    "llr": -0.09331115913099264,
    "wins": 383,
    "losses": 389,
    "draws": 668,
    "workers": 3,
    "sprtElo0": 0
  },
  {
    "id": "682dd2536ec7634154f9adb5",
    "username": "Nonlinear",
    "branch": "see-simple-eval",
    "llr": -0.10514058635160195,
    "wins": 234,
    "losses": 242,
    "draws": 452,
    "workers": 3,
    "sprtElo0": 0
  },
  {
    "id": "682dd0fd6ec7634154f9adb1",
    "username": "Nonlinear",
    "branch": "no-lower-bound-reduction",
    "llr": -0.1501779850949663,
    "wins": 245,
    "losses": 258,
    "draws": 393,
    "workers": 3,
    "sprtElo0": 0
  },
  {
    "id": "682d8eb06ec7634154f9ad40",
    "username": "Vizvezdenec",
    "branch": "smPcTwoF10",
    "llr": -0.21830285308459665,
    "wins": 3956,
    "losses": 3953,
    "draws": 7323,
    "workers": 3,
    "sprtElo0": 0
  },
  {
    "id": "682a6df76ec7634154f9a642",
    "username": "Fisherman",
    "branch": "PR6071",
    "llr": -0.26153639895053166,
    "wins": 182469,
    "losses": 181459,
    "draws": 337864,
    "workers": 7,
    "sprtElo0": 0
  },
  {
    "id": "682dcb196ec7634154f9ada1",
    "username": "AliceRoselia",
    "branch": "Alternate_move_history",
    "llr": -0.34689228156569574,
    "wins": 1138,
    "losses": 1162,
    "draws": 2276,
    "workers": 6,
    "sprtElo0": 0
  },
  {
    "id": "682b06366ec7634154f9aa1b",
    "username": "fauzi2",
    "branch": "newtt1",
    "llr": -0.37436546513813485,
    "wins": 15473,
    "losses": 15381,
    "draws": 29320,
    "workers": 11,
    "sprtElo0": 0.5
  },
  {
    "id": "682b289a6ec7634154f9aa5e",
    "username": "Vizvezdenec",
    "branch": "smPcTwoF5",
    "llr": -0.5404765170630512,
    "wins": 34685,
    "losses": 34537,
    "draws": 64282,
    "workers": 6,
    "sprtElo0": 0
  },
  {
    "id": "682b494c6ec7634154f9aaa1",
    "username": "fauzi2",
    "branch": "simp182",
    "llr": -0.5624758719113426,
    "wins": 26388,
    "losses": 26550,
    "draws": 49430,
    "workers": 5,
    "sprtElo0": -1.75
  },
  {
    "id": "682dacfb6ec7634154f9ad6c",
    "username": "Fisherman",
    "branch": "PsLegal2",
    "llr": -0.6088314132134334,
    "wins": 2412,
    "losses": 2450,
    "draws": 4418,
    "workers": 5,
    "sprtElo0": 0
  },
  {
    "id": "682d8e606ec7634154f9ad3e",
    "username": "Vizvezdenec",
    "branch": "smPcTwoF9",
    "llr": -1.0096583364495488,
    "wins": 4731,
    "losses": 4793,
    "draws": 8972,
    "workers": 6,
    "sprtElo0": 0
  },
  {
    "id": "682b28ed6ec7634154f9aa60",
    "username": "Vizvezdenec",
    "branch": "smPcTwoF6",
    "llr": -1.08797430018974,
    "wins": 35018,
    "losses": 34915,
    "draws": 65971,
    "workers": 4,
    "sprtElo0": 0
  },
  {
    "id": "682b73176ec7634154f9aad4",
    "username": "shawnxu",
    "branch": "test1396",
    "llr": -1.100272237970121,
    "wins": 33556,
    "losses": 33463,
    "draws": 62869,
    "workers": 4,
    "sprtElo0": 0
  },
  {
    "id": "6828ff126ec7634154f99bb3",
    "username": "DanSamek",
    "branch": "rm_razoring",
    "llr": -1.1522091097175335,
    "wins": 6408,
    "losses": 6448,
    "draws": 12108,
    "workers": 0,
    "sprtElo0": 0.5
  },
  {
    "id": "682244603629b02d74b17b4f",
    "username": "0x539",
    "branch": "movepick-tune",
    "llr": -1.2194128573372205,
    "wins": 24101,
    "losses": 24009,
    "draws": 46318,
    "workers": 0,
    "sprtElo0": 0.5
  },
  {
    "id": "682a65d26ec7634154f9a61d",
    "username": "shawnxu",
    "branch": "test1390",
    "llr": -1.3082230859390829,
    "wins": 115723,
    "losses": 116333,
    "draws": 216456,
    "workers": 5,
    "sprtElo0": -1.75
  },
  {
    "id": "682ca5506ec7634154f9ac62",
    "username": "shawnxu",
    "branch": "test1395",
    "llr": -1.3868641647916495,
    "wins": 9227,
    "losses": 9266,
    "draws": 17843,
    "workers": 12,
    "sprtElo0": 0.5
  },
  {
    "id": "682dbd9d6ec7634154f9ad8d",
    "username": "fauzi2",
    "branch": "insee",
    "llr": -1.4330028205761063,
    "wins": 1000,
    "losses": 1121,
    "draws": 2071,
    "workers": 3,
    "sprtElo0": 0
  },
  {
    "id": "682b2f7c6ec7634154f9aa73",
    "username": "DanSamek",
    "branch": "ext_stuff_1",
    "llr": -1.5727447482330896,
    "wins": 47901,
    "losses": 47773,
    "draws": 88902,
    "workers": 4,
    "sprtElo0": 0
  },
  {
    "id": "682c3a3d6ec7634154f9abba",
    "username": "pb00067",
    "branch": "exp377",
    "llr": -1.7058996683121705,
    "wins": 30894,
    "losses": 30870,
    "draws": 57596,
    "workers": 2,
    "sprtElo0": 0
  },
  {
    "id": "682bbffc6ec7634154f9ab37",
    "username": "Nonlinear",
    "branch": "static-eval-difference-reduction",
    "llr": -1.8685793818652512,
    "wins": 24237,
    "losses": 24265,
    "draws": 45162,
    "workers": 6,
    "sprtElo0": 0
  },
  {
    "id": "682a80176ec7634154f9a66a",
    "username": "Nonlinear",
    "branch": "no-lower-bound-reduction",
    "llr": -1.9529765724750143,
    "wins": 44949,
    "losses": 44869,
    "draws": 82502,
    "workers": 2,
    "sprtElo0": 0
  },
  {
    "id": "682b56726ec7634154f9aab7",
    "username": "Saphereye",
    "branch": "improve_movepick",
    "llr": -2.2220669242368913,
    "wins": 48825,
    "losses": 48748,
    "draws": 91611,
    "workers": 7,
    "sprtElo0": 0
  },
  {
    "id": "682a6e1b6ec7634154f9a645",
    "username": "0x539",
    "branch": "score-king2",
    "llr": -2.419899100302985,
    "wins": 30353,
    "losses": 30396,
    "draws": 56083,
    "workers": 0,
    "sprtElo0": 0
  },
  {
    "id": "682c758a6ec7634154f9ac2b",
    "username": "pb00067",
    "branch": "see_knightFork2",
    "llr": -2.598788003911926,
    "wins": 25953,
    "losses": 26035,
    "draws": 48844,
    "workers": 4,
    "sprtElo0": 0
  },
  {
    "id": "682a816a6ec7634154f9a66e",
    "username": "0x539",
    "branch": "score-king2",
    "llr": -2.6024880785942406,
    "wins": 33470,
    "losses": 33510,
    "draws": 62780,
    "workers": 0,
    "sprtElo0": 0
  },
  {
    "id": "682b6ae06ec7634154f9aacc",
    "username": "fauzi2",
    "branch": "smallt",
    "llr": null,
    "wins": 4346,
    "losses": 4377,
    "draws": 8167,
    "workers": 9,
    "sprtElo0": null
  },
  {
    "id": "682db89b6ec7634154f9ad84",
    "username": "fauzi2",
    "branch": "rdtm4d",
    "llr": null,
    "wins": 630,
    "losses": 656,
    "draws": 1190,
    "workers": 10,
    "sprtElo0": null
  }
]