[
  {
    "id": "6849d37ee84567164b5c9ec9",
    "username": "shawnxu",
    "branch": "test1461",
    "llr": 2.315915500643267,
    "wins": 111064,
    "losses": 110233,
    "draws": 208559,
    "workers": 5,
    "sprtElo0": 0
  },
  {
    "id": "684f5301703522d4f129cade",
    "username": "Fisherman",
    "branch": "QSTweak",
    "llr": 2.0831417814822055,
    "wins": 15840,
    "losses": 15568,
    "draws": 29200,
    "workers": 5,
    "sprtElo0": 0
  },
  {
    "id": "684c1b8c703522d4f129c5b5",
    "username": "Nonlinear",
    "branch": "check-static-eval-3",
    "llr": 1.5776385003843396,
    "wins": 34081,
    "losses": 33749,
    "draws": 64042,
    "workers": 4,
    "sprtElo0": 0
  },
  {
    "id": "684a2701e84567164b5c9f86",
    "username": "ergodice",
    "branch": "badsimp1",
    "llr": 1.219741091143534,
    "wins": 13753,
    "losses": 13708,
    "draws": 26341,
    "workers": 0,
    "sprtElo0": -1.75
  },
  {
    "id": "684e1aa8703522d4f129c9f2",
    "username": "sg",
    "branch": "tweak_cap_order3",
    "llr": 1.1227877749418926,
    "wins": 20509,
    "losses": 20293,
    "draws": 38942,
    "workers": 5,
    "sprtElo0": 0
  },
  {
    "id": "684f0396703522d4f129caa0",
    "username": "shawnxu",
    "branch": "test1467",
    "llr": 1.0953475837182767,
    "wins": 9316,
    "losses": 9166,
    "draws": 17158,
    "workers": 3,
    "sprtElo0": 0
  },
  {
    "id": "684f24ce703522d4f129cab5",
    "username": "ergodice",
    "branch": "lmrpv1",
    "llr": 0.9643522898432438,
    "wins": 9960,
    "losses": 9917,
    "draws": 18811,
    "workers": 5,
    "sprtElo0": -1.75
  },
  {
    "id": "684e16ee703522d4f129c9e9",
    "username": "ergodice",
    "branch": "simps61425a",
    "llr": 0.47973740164415885,
    "wins": 19780,
    "losses": 19822,
    "draws": 37326,
    "workers": 5,
    "sprtElo0": -1.75
  },
  {
    "id": "684f37fb703522d4f129caca",
    "username": "fauzi2",
    "branch": "ctol2",
    "llr": 0.38438579146596685,
    "wins": 6202,
    "losses": 6134,
    "draws": 11568,
    "workers": 2,
    "sprtElo0": 0
  },
  {
    "id": "684f65a0703522d4f129cae5",
    "username": "sg",
    "branch": "tweak_cap_history4",
    "llr": 0.374059532490425,
    "wins": 7035,
    "losses": 6963,
    "draws": 12850,
    "workers": 4,
    "sprtElo0": 0
  },
  {
    "id": "684decd0703522d4f129c9c4",
    "username": "sg",
    "branch": "tweak_cap_order2",
    "llr": 0.3379394026419402,
    "wins": 2249,
    "losses": 2207,
    "draws": 4056,
    "workers": 3,
    "sprtElo0": 0
  },
  {
    "id": "68486106b1a2b107ef24f9b9",
    "username": "DanSamek",
    "branch": "tt_cap_cm_bonus_1",
    "llr": 0.11546696070441388,
    "wins": 68859,
    "losses": 68459,
    "draws": 129818,
    "workers": 0,
    "sprtElo0": 0
  },
  {
    "id": "684db429703522d4f129c9a5",
    "username": "fauzi2",
    "branch": "tdet",
    "llr": 0.019981679902938726,
    "wins": 16773,
    "losses": 16676,
    "draws": 31671,
    "workers": 2,
    "sprtElo0": 0
  },
  {
    "id": "684f37ff703522d4f129cacc",
    "username": "fauzi2",
    "branch": "ctol3",
    "llr": 0.008796268052188378,
    "wins": 6974,
    "losses": 6934,
    "draws": 13036,
    "workers": 2,
    "sprtElo0": 0
  },
  {
    "id": "6848d841e84567164b5c9bdd",
    "username": "fauzi2",
    "branch": "ttag",
    "llr": 0,
    "wins": 0,
    "losses": 0,
    "draws": 0,
    "workers": 0,
    "sprtElo0": 0.5
  },
  {
    "id": "68459c9f375c2b77d98553c8",
    "username": "fauzi2",
    "branch": "cude",
    "llr": -0.029452893472993586,
    "wins": 186,
    "losses": 187,
    "draws": 317,
    "workers": 0,
    "sprtElo0": 0.5
  },
  {
    "id": "684d1c78703522d4f129c93d",
    "username": "Vizvezdenec",
    "branch": "moreCtc2",
    "llr": -0.10090754448325513,
    "wins": 26545,
    "losses": 26404,
    "draws": 49995,
    "workers": 4,
    "sprtElo0": 0
  },
  {
    "id": "684f27cd703522d4f129cac0",
    "username": "ergodice",
    "branch": "probcutreturn",
    "llr": -0.10371483249011006,
    "wins": 10417,
    "losses": 10471,
    "draws": 19752,
    "workers": 5,
    "sprtElo0": -1.75
  },
  {
    "id": "684dae82703522d4f129c9a2",
    "username": "Vizvezdenec",
    "branch": "cnAfterNmp7",
    "llr": -0.11141184467269911,
    "wins": 12116,
    "losses": 12029,
    "draws": 23045,
    "workers": 3,
    "sprtElo0": 0.5
  },
  {
    "id": "684f37f2703522d4f129cac6",
    "username": "fauzi2",
    "branch": "ctol",
    "llr": -0.20593687040367128,
    "wins": 5163,
    "losses": 5152,
    "draws": 9621,
    "workers": 3,
    "sprtElo0": 0
  },
  {
    "id": "684f3b58703522d4f129cad3",
    "username": "sg",
    "branch": "tweak_cap_order5",
    "llr": -0.23652718198340456,
    "wins": 8159,
    "losses": 8133,
    "draws": 15804,
    "workers": 1,
    "sprtElo0": 0
  },
  {
    "id": "684638b6ce2583915b6b0448",
    "username": "sg",
    "branch": "tweak_less_lmr7",
    "llr": -0.2671268383989175,
    "wins": 55920,
    "losses": 55629,
    "draws": 104643,
    "workers": 0,
    "sprtElo0": 0
  },
  {
    "id": "68489fb2e84567164b5c9bb4",
    "username": "sg",
    "branch": "tweak_more_lmr2",
    "llr": -0.26983112107913,
    "wins": 45815,
    "losses": 45580,
    "draws": 86429,
    "workers": 0,
    "sprtElo0": 0
  },
  {
    "id": "684bd1f0703522d4f129c56b",
    "username": "snicolet",
    "branch": "mat2",
    "llr": -0.27255460125687037,
    "wins": 8977,
    "losses": 8950,
    "draws": 17145,
    "workers": 0,
    "sprtElo0": 0
  },
  {
    "id": "6850313e703522d4f129cb81",
    "username": "DanSamek",
    "branch": "nph",
    "llr": -0.3205537602892019,
    "wins": 448,
    "losses": 473,
    "draws": 871,
    "workers": 2,
    "sprtElo0": 0
  },
  {
    "id": "68503554703522d4f129cb8e",
    "username": "sg",
    "branch": "tweak_cap_order6",
    "llr": -0.3380953571785177,
    "wins": 310,
    "losses": 338,
    "draws": 600,
    "workers": 2,
    "sprtElo0": 0
  },
  {
    "id": "6849a58fe84567164b5c9d81",
    "username": "sg",
    "branch": "tweak_more_lmr3",
    "llr": -0.3768891016355694,
    "wins": 26751,
    "losses": 26632,
    "draws": 50905,
    "workers": 0,
    "sprtElo0": 0
  },
  {
    "id": "684f6931703522d4f129caec",
    "username": "Vizvezdenec",
    "branch": "moreCtc4",
    "llr": -0.47114259963867067,
    "wins": 6293,
    "losses": 6298,
    "draws": 12337,
    "workers": 1,
    "sprtElo0": 0
  },
  {
    "id": "6848a38de84567164b5c9bbb",
    "username": "fauzi2",
    "branch": "ttag1",
    "llr": -0.5117769915611596,
    "wins": 55784,
    "losses": 55514,
    "draws": 104766,
    "workers": 2,
    "sprtElo0": 0
  },
  {
    "id": "684c1ea1703522d4f129c5b9",
    "username": "Nonlinear",
    "branch": "smallnet-cv",
    "llr": -0.5839144979039014,
    "wins": 32059,
    "losses": 31930,
    "draws": 60491,
    "workers": 2,
    "sprtElo0": 0
  },
  {
    "id": "68456861375c2b77d9855360",
    "username": "sg",
    "branch": "tweak_less_lmr6",
    "llr": -0.7043226320537266,
    "wins": 32852,
    "losses": 32728,
    "draws": 61940,
    "workers": 0,
    "sprtElo0": 0
  },
  {
    "id": "684f68e5703522d4f129caea",
    "username": "Vizvezdenec",
    "branch": "moreCtc3",
    "llr": -0.708062409650105,
    "wins": 6889,
    "losses": 6913,
    "draws": 12598,
    "workers": 4,
    "sprtElo0": 0
  },
  {
    "id": "684ad814e84567164b5ca069",
    "username": "sg",
    "branch": "tweak_more_lmr4",
    "llr": -0.709630331915314,
    "wins": 7739,
    "losses": 7758,
    "draws": 14327,
    "workers": 0,
    "sprtElo0": 0
  },
  {
    "id": "684d4d51703522d4f129c961",
    "username": "Nonlinear",
    "branch": "allnode-bonusscale-thing",
    "llr": -0.7631456721162767,
    "wins": 23541,
    "losses": 23475,
    "draws": 44408,
    "workers": 5,
    "sprtElo0": 0
  },
  {
    "id": "684ec176703522d4f129ca67",
    "username": "fauzi2",
    "branch": "simp169c",
    "llr": -0.8309896183916246,
    "wins": 8629,
    "losses": 8739,
    "draws": 16616,
    "workers": 3,
    "sprtElo0": -1.75
  },
  {
    "id": "68475e5d80918a66caa2eec2",
    "username": "sg",
    "branch": "tweak_less_lmr8",
    "llr": -0.8387884279433894,
    "wins": 32905,
    "losses": 32794,
    "draws": 61373,
    "workers": 0,
    "sprtElo0": 0
  },
  {
    "id": "684958dde84567164b5c9c66",
    "username": "Fisherman",
    "branch": "QSTweak",
    "llr": -0.8476171102720911,
    "wins": 46444,
    "losses": 46144,
    "draws": 88168,
    "workers": 8,
    "sprtElo0": 0.5
  },
  {
    "id": "684d3b00703522d4f129c949",
    "username": "DanSamek",
    "branch": "mc_bl",
    "llr": -0.9164552990677463,
    "wins": 41483,
    "losses": 41331,
    "draws": 78018,
    "workers": 3,
    "sprtElo0": 0
  },
  {
    "id": "684f9457703522d4f129cb01",
    "username": "kokodio",
    "branch": "patch-35",
    "llr": -0.924859114129702,
    "wins": 8149,
    "losses": 8184,
    "draws": 15411,
    "workers": 4,
    "sprtElo0": 0
  },
  {
    "id": "684da2db703522d4f129c993",
    "username": "DanSamek",
    "branch": "tt_cap_cm_bonus_2",
    "llr": -0.9735253149993338,
    "wins": 18507,
    "losses": 18440,
    "draws": 35263,
    "workers": 6,
    "sprtElo0": 0.5
  },
  {
    "id": "6844d12e1d7aa377ed9cef24",
    "username": "sg",
    "branch": "tweak_less_lmr3",
    "llr": -1.0513746614532948,
    "wins": 6106,
    "losses": 6163,
    "draws": 11571,
    "workers": 0,
    "sprtElo0": 0
  },
  {
    "id": "684bbfe6703522d4f129c54c",
    "username": "kokodio",
    "branch": "patch-35",
    "llr": -1.079797526913916,
    "wins": 61029,
    "losses": 60779,
    "draws": 114320,
    "workers": 4,
    "sprtElo0": 0
  },
  {
    "id": "684e1225703522d4f129c9de",
    "username": "Nonlinear",
    "branch": "cv-improving",
    "llr": -1.0996071469391349,
    "wins": 17805,
    "losses": 17801,
    "draws": 33578,
    "workers": 3,
    "sprtElo0": 0
  },
  {
    "id": "684f1779703522d4f129caae",
    "username": "ergodice",
    "branch": "subext2",
    "llr": -1.1277930552619413,
    "wins": 10683,
    "losses": 10722,
    "draws": 20003,
    "workers": 5,
    "sprtElo0": 0
  },
  {
    "id": "684f01a6703522d4f129ca9c",
    "username": "RaskiTech",
    "branch": "modifiedBranch",
    "llr": -1.1749202022491338,
    "wins": 17498,
    "losses": 17502,
    "draws": 33096,
    "workers": 6,
    "sprtElo0": 0
  },
  {
    "id": "684d6b56703522d4f129c979",
    "username": "sg",
    "branch": "tweak_more_lmr7",
    "llr": -1.204166072279198,
    "wins": 2316,
    "losses": 2409,
    "draws": 4363,
    "workers": 0,
    "sprtElo0": 0
  },
  {
    "id": "684d5cb7703522d4f129c971",
    "username": "sg",
    "branch": "tweak_less_lmr9",
    "llr": -1.2398816280183362,
    "wins": 2554,
    "losses": 2649,
    "draws": 5069,
    "workers": 0,
    "sprtElo0": 0
  },
  {
    "id": "68494cece84567164b5c9c4f",
    "username": "pb00067",
    "branch": "avoidSEEonKingMove",
    "llr": -1.348793858097421,
    "wins": 36239,
    "losses": 36157,
    "draws": 68212,
    "workers": 3,
    "sprtElo0": 0
  },
  {
    "id": "684eca5c703522d4f129ca76",
    "username": "sg",
    "branch": "tweak_cap_order4",
    "llr": -1.3494240911021202,
    "wins": 3522,
    "losses": 3620,
    "draws": 6906,
    "workers": 0,
    "sprtElo0": 0
  },
  {
    "id": "6845301f1d7aa377ed9cf128",
    "username": "sg",
    "branch": "tweak_less_lmr5",
    "llr": -1.3567972637102437,
    "wins": 47661,
    "losses": 47509,
    "draws": 90718,
    "workers": 0,
    "sprtElo0": 0
  },
  {
    "id": "684e0414703522d4f129c9ca",
    "username": "sg",
    "branch": "tweak_cap_history2",
    "llr": -1.3778290172492118,
    "wins": 18259,
    "losses": 18277,
    "draws": 34312,
    "workers": 2,
    "sprtElo0": 0
  },
  {
    "id": "6849ab97e84567164b5c9ddf",
    "username": "Vizvezdenec",
    "branch": "cnAfterNmp8",
    "llr": -1.4140585315092646,
    "wins": 54419,
    "losses": 54236,
    "draws": 102801,
    "workers": 4,
    "sprtElo0": 0
  },
  {
    "id": "684bd1ae703522d4f129c569",
    "username": "snicolet",
    "branch": "mat2",
    "llr": -1.4354840419558683,
    "wins": 8046,
    "losses": 8126,
    "draws": 15508,
    "workers": 0,
    "sprtElo0": 0
  },
  {
    "id": "684f37f6703522d4f129cac8",
    "username": "fauzi2",
    "branch": "ctol1",
    "llr": -1.4571462335991345,
    "wins": 5587,
    "losses": 5681,
    "draws": 10492,
    "workers": 3,
    "sprtElo0": 0
  },
  {
    "id": "684dcc38703522d4f129c9bc",
    "username": "sg",
    "branch": "tweak_cap_history",
    "llr": -1.497955718034725,
    "wins": 1090,
    "losses": 1218,
    "draws": 2140,
    "workers": 0,
    "sprtElo0": 0
  },
  {
    "id": "684e1833703522d4f129c9ee",
    "username": "sg",
    "branch": "tweak_less_lmr10",
    "llr": -1.5506987046026641,
    "wins": 9819,
    "losses": 9899,
    "draws": 19002,
    "workers": 0,
    "sprtElo0": 0
  },
  {
    "id": "68493701e84567164b5c9c33",
    "username": "pb00067",
    "branch": "mpDeliverLegal",
    "llr": -1.5512765526773382,
    "wins": 19000,
    "losses": 19207,
    "draws": 36161,
    "workers": 0,
    "sprtElo0": -1.75
  },
  {
    "id": "684eff4f703522d4f129ca96",
    "username": "shawnxu",
    "branch": "test1466",
    "llr": -1.628719885892715,
    "wins": 12258,
    "losses": 12453,
    "draws": 23481,
    "workers": 4,
    "sprtElo0": -1.75
  },
  {
    "id": "684e197a703522d4f129c9f0",
    "username": "ergodice",
    "branch": "statscoreconstants",
    "llr": -1.6300233001379603,
    "wins": 17599,
    "losses": 17817,
    "draws": 33352,
    "workers": 4,
    "sprtElo0": -1.75
  },
  {
    "id": "6841e632b3a7bbdcda9a4527",
    "username": "sg",
    "branch": "tweak_more_lmr",
    "llr": -1.6381960213731708,
    "wins": 48122,
    "losses": 47995,
    "draws": 90667,
    "workers": 0,
    "sprtElo0": 0
  },
  {
    "id": "6844dfd41d7aa377ed9cef44",
    "username": "sg",
    "branch": "tweak_less_lmr4",
    "llr": -1.7562927275138382,
    "wins": 45574,
    "losses": 45470,
    "draws": 85980,
    "workers": 2,
    "sprtElo0": 0
  },
  {
    "id": "6848a389e84567164b5c9bb9",
    "username": "fauzi2",
    "branch": "ttag",
    "llr": -1.8412285406745175,
    "wins": 62558,
    "losses": 62367,
    "draws": 117347,
    "workers": 4,
    "sprtElo0": 0
  },
  {
    "id": "684b1d4ce84567164b5ca0ae",
    "username": "sg",
    "branch": "tweak_more_lmr5",
    "llr": -1.8830656890047426,
    "wins": 5552,
    "losses": 5686,
    "draws": 10682,
    "workers": 0,
    "sprtElo0": 0
  },
  {
    "id": "6847386e80918a66caa2ee91",
    "username": "Vizvezdenec",
    "branch": "cnAfterNmp5",
    "llr": -2.2027417729770122,
    "wins": 104015,
    "losses": 103623,
    "draws": 195114,
    "workers": 1,
    "sprtElo0": 0
  },
  {
    "id": "683bb8476ec7634154f9d866",
    "username": "0x539",
    "branch": "score-king2",
    "llr": -2.203963590186707,
    "wins": 31387,
    "losses": 31403,
    "draws": 59290,
    "workers": 0,
    "sprtElo0": 0
  },
  {
    "id": "6849e082e84567164b5c9f10",
    "username": "Nonlinear",
    "branch": "tt-next-hist",
    "llr": -2.2067369799736634,
    "wins": 29375,
    "losses": 29322,
    "draws": 56269,
    "workers": 5,
    "sprtElo0": 0.5
  },
  {
    "id": "684d4b6d703522d4f129c95b",
    "username": "Nonlinear",
    "branch": "smallnet-cv",
    "llr": -2.2277712085593433,
    "wins": 22967,
    "losses": 23032,
    "draws": 43569,
    "workers": 5,
    "sprtElo0": 0
  },
  {
    "id": "684dc345703522d4f129c9b4",
    "username": "sg",
    "branch": "tweak_cap_order",
    "llr": -2.3903927054896896,
    "wins": 8339,
    "losses": 8501,
    "draws": 16056,
    "workers": 0,
    "sprtElo0": 0
  },
  {
    "id": "684f06b7703522d4f129caa2",
    "username": "shawnxu",
    "branch": "test1468",
    "llr": -2.639751300374661,
    "wins": 12296,
    "losses": 12459,
    "draws": 22989,
    "workers": 2,
    "sprtElo0": 0
  },
  {
    "id": "684f2756703522d4f129cabe",
    "username": "shawnxu",
    "branch": "test1470",
    "llr": -2.678209774417036,
    "wins": 9787,
    "losses": 9968,
    "draws": 18325,
    "workers": 4,
    "sprtElo0": 0
  }
]