[
  {
    "id": "6829fe1b6ec7634154f9a036",
    "username": "fauzi2",
    "branch": "rdtm4b",
    "llr": 1.4634217097616395,
    "wins": 68271,
    "losses": 67622,
    "draws": 130531,
    "workers": 12,
    "sprtElo0": 0.5
  },
  {
    "id": "682b494c6ec7634154f9aaa1",
    "username": "fauzi2",
    "branch": "simp182",
    "llr": 1.3688063912876336,
    "wins": 41391,
    "losses": 41446,
    "draws": 77451,
    "workers": 4,
    "sprtElo0": -1.75
  },
  {
    "id": "682a32aa6ec7634154f9a372",
    "username": "fauzi2",
    "branch": "rdtm4c",
    "llr": 0.9692542946823571,
    "wins": 66006,
    "losses": 65414,
    "draws": 126622,
    "workers": 9,
    "sprtElo0": 0.5
  },
  {
    "id": "682e754a6ec7634154f9af30",
    "username": "ergodice",
    "branch": "truepv1",
    "llr": 0.5722114925814872,
    "wins": 8841,
    "losses": 8740,
    "draws": 16563,
    "workers": 5,
    "sprtElo0": 0
  },
  {
    "id": "682a45b16ec7634154f9a3b3",
    "username": "shawnxu",
    "branch": "test1383",
    "llr": 0.37566452468969275,
    "wins": 48531,
    "losses": 48268,
    "draws": 91125,
    "workers": 17,
    "sprtElo0": 0
  },
  {
    "id": "682eeaa56ec7634154f9afb8",
    "username": "yT7Af9Fc",
    "branch": "patch-14",
    "llr": 0.2769256668822569,
    "wins": 154,
    "losses": 130,
    "draws": 274,
    "workers": 15,
    "sprtElo0": 0.5
  },
  {
    "id": "682e329e6ec7634154f9ae2d",
    "username": "ergodice",
    "branch": "hindsightred7",
    "llr": 0.18309305359471706,
    "wins": 11768,
    "losses": 11685,
    "draws": 22179,
    "workers": 4,
    "sprtElo0": 0
  },
  {
    "id": "682dd10d6ec7634154f9adb3",
    "username": "pb00067",
    "branch": "stalemateDetect",
    "llr": 0.1776014396706842,
    "wins": 10497,
    "losses": 10524,
    "draws": 20049,
    "workers": 9,
    "sprtElo0": -1.75
  },
  {
    "id": "682ed6e86ec7634154f9af8f",
    "username": "Vizvezdenec",
    "branch": "lowplyCH2",
    "llr": 0.17733582882839796,
    "wins": 1132,
    "losses": 1110,
    "draws": 2174,
    "workers": 7,
    "sprtElo0": 0
  },
  {
    "id": "682dd0966ec7634154f9adab",
    "username": "Nonlinear",
    "branch": "no-lower-bound-reduction",
    "llr": -0.0877281027506639,
    "wins": 10460,
    "losses": 10409,
    "draws": 19387,
    "workers": 3,
    "sprtElo0": 0
  },
  {
    "id": "682ed6756ec7634154f9af8c",
    "username": "Vizvezdenec",
    "branch": "lowplyCH1",
    "llr": -0.1100997820537575,
    "wins": 1189,
    "losses": 1192,
    "draws": 2227,
    "workers": 3,
    "sprtElo0": 0
  },
  {
    "id": "682b06366ec7634154f9aa1b",
    "username": "fauzi2",
    "branch": "newtt1",
    "llr": -0.3138711640735875,
    "wins": 22245,
    "losses": 22094,
    "draws": 42349,
    "workers": 7,
    "sprtElo0": 0.5
  },
  {
    "id": "682ed7686ec7634154f9af92",
    "username": "Vizvezdenec",
    "branch": "lowplyCH3",
    "llr": -0.38330860898263774,
    "wins": 1048,
    "losses": 1076,
    "draws": 2004,
    "workers": 4,
    "sprtElo0": 0
  },
  {
    "id": "682ee57a6ec7634154f9afa7",
    "username": "AliceRoselia",
    "branch": "Sacrifice_extension",
    "llr": -0.4074358563476972,
    "wins": 957,
    "losses": 988,
    "draws": 1703,
    "workers": 5,
    "sprtElo0": 0
  },
  {
    "id": "682ee37d6ec7634154f9afa4",
    "username": "kokodio",
    "branch": "patch-3",
    "llr": -0.44693169291580187,
    "wins": 831,
    "losses": 866,
    "draws": 1535,
    "workers": 3,
    "sprtElo0": 0
  },
  {
    "id": "682b792b6ec7634154f9aae7",
    "username": "Fisherman",
    "branch": "SortLess",
    "llr": -0.49655035072193476,
    "wins": 60636,
    "losses": 60336,
    "draws": 113236,
    "workers": 5,
    "sprtElo0": 0
  },
  {
    "id": "682e73316ec7634154f9af23",
    "username": "shawnxu",
    "branch": "test1399",
    "llr": -0.5573861242762641,
    "wins": 5658,
    "losses": 5675,
    "draws": 10715,
    "workers": 4,
    "sprtElo0": 0
  },
  {
    "id": "682dd0fd6ec7634154f9adb1",
    "username": "Nonlinear",
    "branch": "no-lower-bound-reduction",
    "llr": -0.6040309457729364,
    "wins": 10468,
    "losses": 10462,
    "draws": 19614,
    "workers": 5,
    "sprtElo0": 0
  },
  {
    "id": "682ed7a66ec7634154f9af94",
    "username": "kokodio",
    "branch": "patch-2",
    "llr": -0.8319715700812045,
    "wins": 1721,
    "losses": 1785,
    "draws": 3438,
    "workers": 4,
    "sprtElo0": 0
  },
  {
    "id": "682a6df76ec7634154f9a642",
    "username": "Fisherman",
    "branch": "PR6071",
    "llr": -0.9172867912157989,
    "wins": 217715,
    "losses": 216564,
    "draws": 403513,
    "workers": 5,
    "sprtElo0": 0
  },
  {
    "id": "682e73a96ec7634154f9af2b",
    "username": "shawnxu",
    "branch": "test1398",
    "llr": -1.0218908296037037,
    "wins": 6218,
    "losses": 6273,
    "draws": 11573,
    "workers": 2,
    "sprtElo0": 0
  },
  {
    "id": "682dd2536ec7634154f9adb5",
    "username": "Nonlinear",
    "branch": "see-simple-eval",
    "llr": -1.1359151371098848,
    "wins": 8991,
    "losses": 9040,
    "draws": 16977,
    "workers": 3,
    "sprtElo0": 0
  },
  {
    "id": "6828ff126ec7634154f99bb3",
    "username": "DanSamek",
    "branch": "rm_razoring",
    "llr": -1.1522091097175335,
    "wins": 6408,
    "losses": 6448,
    "draws": 12108,
    "workers": 0,
    "sprtElo0": 0.5
  },
  {
    "id": "682244603629b02d74b17b4f",
    "username": "0x539",
    "branch": "movepick-tune",
    "llr": -1.2194128573372205,
    "wins": 24101,
    "losses": 24009,
    "draws": 46318,
    "workers": 0,
    "sprtElo0": 0.5
  },
  {
    "id": "682b2f7c6ec7634154f9aa73",
    "username": "DanSamek",
    "branch": "ext_stuff_1",
    "llr": -1.251392793380574,
    "wins": 75325,
    "losses": 75020,
    "draws": 139447,
    "workers": 4,
    "sprtElo0": 0
  },
  {
    "id": "682b289a6ec7634154f9aa5e",
    "username": "Vizvezdenec",
    "branch": "smPcTwoF5",
    "llr": -1.258553633783358,
    "wins": 51620,
    "losses": 51440,
    "draws": 95820,
    "workers": 3,
    "sprtElo0": 0
  },
  {
    "id": "682d78a36ec7634154f9ad1f",
    "username": "Fisherman",
    "branch": "MPOverwriteFix",
    "llr": -1.2864391614116122,
    "wins": 28565,
    "losses": 28801,
    "draws": 53450,
    "workers": 3,
    "sprtElo0": -1.75
  },
  {
    "id": "682dd0cf6ec7634154f9adad",
    "username": "Nonlinear",
    "branch": "no-lower-bound-reduction",
    "llr": -1.318457360293826,
    "wins": 11417,
    "losses": 11468,
    "draws": 21755,
    "workers": 4,
    "sprtElo0": 0
  },
  {
    "id": "682e57846ec7634154f9aefa",
    "username": "shawnxu",
    "branch": "test1397",
    "llr": -1.3224983301091378,
    "wins": 3504,
    "losses": 3583,
    "draws": 6509,
    "workers": 9,
    "sprtElo0": 0.5
  },
  {
    "id": "682b28ed6ec7634154f9aa60",
    "username": "Vizvezdenec",
    "branch": "smPcTwoF6",
    "llr": -1.542101456272483,
    "wins": 52024,
    "losses": 51865,
    "draws": 97743,
    "workers": 4,
    "sprtElo0": 0
  },
  {
    "id": "682bbffc6ec7634154f9ab37",
    "username": "Nonlinear",
    "branch": "static-eval-difference-reduction",
    "llr": -1.6410994269859935,
    "wins": 34266,
    "losses": 34217,
    "draws": 64061,
    "workers": 3,
    "sprtElo0": 0
  },
  {
    "id": "682b73176ec7634154f9aad4",
    "username": "shawnxu",
    "branch": "test1396",
    "llr": -2.0409091738757783,
    "wins": 49711,
    "losses": 49609,
    "draws": 93480,
    "workers": 4,
    "sprtElo0": 0
  },
  {
    "id": "682e9c456ec7634154f9af49",
    "username": "sg",
    "branch": "skip_lmr_history3",
    "llr": -2.1615385930461013,
    "wins": 5522,
    "losses": 5678,
    "draws": 10464,
    "workers": 9,
    "sprtElo0": 0
  },
  {
    "id": "682d8e606ec7634154f9ad3e",
    "username": "Vizvezdenec",
    "branch": "smPcTwoF9",
    "llr": -2.231420423171597,
    "wins": 21384,
    "losses": 21460,
    "draws": 39940,
    "workers": 4,
    "sprtElo0": 0
  },
  {
    "id": "682a80176ec7634154f9a66a",
    "username": "Nonlinear",
    "branch": "no-lower-bound-reduction",
    "llr": -2.3215723627060325,
    "wins": 56300,
    "losses": 56188,
    "draws": 103832,
    "workers": 4,
    "sprtElo0": 0
  },
  {
    "id": "682a6e1b6ec7634154f9a645",
    "username": "0x539",
    "branch": "score-king2",
    "llr": -2.419899100302985,
    "wins": 30353,
    "losses": 30396,
    "draws": 56083,
    "workers": 0,
    "sprtElo0": 0
  },
  {
    "id": "682e7f176ec7634154f9af37",
    "username": "sg",
    "branch": "skip_lmr_history2",
    "llr": -2.445185094090654,
    "wins": 6897,
    "losses": 7066,
    "draws": 13365,
    "workers": 5,
    "sprtElo0": 0
  },
  {
    "id": "682e32686ec7634154f9ae2b",
    "username": "ergodice",
    "branch": "hindsightred6",
    "llr": -2.4787952666850783,
    "wins": 12054,
    "losses": 12204,
    "draws": 22654,
    "workers": 2,
    "sprtElo0": 0
  },
  {
    "id": "682dd78b6ec7634154f9adc5",
    "username": "Nonlinear",
    "branch": "implicit-nmp-3",
    "llr": -2.5060727769814504,
    "wins": 8862,
    "losses": 9032,
    "draws": 16634,
    "workers": 3,
    "sprtElo0": 0
  },
  {
    "id": "682a816a6ec7634154f9a66e",
    "username": "0x539",
    "branch": "score-king2",
    "llr": -2.6024880785942406,
    "wins": 33470,
    "losses": 33510,
    "draws": 62780,
    "workers": 0,
    "sprtElo0": 0
  },
  {
    "id": "682ca5506ec7634154f9ac62",
    "username": "shawnxu",
    "branch": "test1395",
    "llr": -2.773754987107209,
    "wins": 17154,
    "losses": 17242,
    "draws": 33224,
    "workers": 7,
    "sprtElo0": 0.5
  },
  {
    "id": "682b6ae06ec7634154f9aacc",
    "username": "fauzi2",
    "branch": "smallt",
    "llr": null,
    "wins": 6629,
    "losses": 6672,
    "draws": 12347,
    "workers": 11,
    "sprtElo0": null
  },
  {
    "id": "682db89b6ec7634154f9ad84",
    "username": "fauzi2",
    "branch": "rdtm4d",
    "llr": null,
    "wins": 6784,
    "losses": 6862,
    "draws": 13138,
    "workers": 8,
    "sprtElo0": null
  }
]