[
  {
    "id": "684ab516e84567164b5ca02f",
    "username": "fauzi2",
    "branch": "simp187",
    "llr": 2.4279933292677343,
    "wins": 9938,
    "losses": 9777,
    "draws": 18577,
    "workers": 10,
    "sprtElo0": -1.75
  },
  {
    "id": "684b557e703522d4f129c4fa",
    "username": "snicolet",
    "branch": "mat2",
    "llr": 1.7799680215083225,
    "wins": 31949,
    "losses": 31613,
    "draws": 60054,
    "workers": 5,
    "sprtElo0": 0
  },
  {
    "id": "6848a389e84567164b5c9bb9",
    "username": "fauzi2",
    "branch": "ttag",
    "llr": 1.434252971261796,
    "wins": 38748,
    "losses": 38404,
    "draws": 73152,
    "workers": 5,
    "sprtElo0": 0
  },
  {
    "id": "684958dde84567164b5c9c66",
    "username": "Fisherman",
    "branch": "QSTweak",
    "llr": 1.2464708476065456,
    "wins": 23404,
    "losses": 23115,
    "draws": 44435,
    "workers": 7,
    "sprtElo0": 0.5
  },
  {
    "id": "684a2701e84567164b5c9f86",
    "username": "ergodice",
    "branch": "badsimp1",
    "llr": 1.219741091143534,
    "wins": 13753,
    "losses": 13708,
    "draws": 26341,
    "workers": 0,
    "sprtElo0": -1.75
  },
  {
    "id": "684bc0f2703522d4f129c54f",
    "username": "kokodio",
    "branch": "patch-35",
    "llr": 0.7420419953515757,
    "wins": 18748,
    "losses": 18576,
    "draws": 35316,
    "workers": 3,
    "sprtElo0": 0
  },
  {
    "id": "684bbfe6703522d4f129c54c",
    "username": "kokodio",
    "branch": "patch-35",
    "llr": 0.7263336178105968,
    "wins": 21557,
    "losses": 21372,
    "draws": 40015,
    "workers": 2,
    "sprtElo0": 0
  },
  {
    "id": "68489fb2e84567164b5c9bb4",
    "username": "sg",
    "branch": "tweak_more_lmr2",
    "llr": 0.7188137879020292,
    "wins": 40359,
    "losses": 40068,
    "draws": 76085,
    "workers": 2,
    "sprtElo0": 0
  },
  {
    "id": "684c5773703522d4f129c5f7",
    "username": "ergodice",
    "branch": "quietstreak1",
    "llr": 0.6416329713731123,
    "wins": 7221,
    "losses": 7195,
    "draws": 13392,
    "workers": 3,
    "sprtElo0": -1.75
  },
  {
    "id": "6848a38de84567164b5c9bbb",
    "username": "fauzi2",
    "branch": "ttag1",
    "llr": 0.6030368110408542,
    "wins": 33698,
    "losses": 33455,
    "draws": 63471,
    "workers": 5,
    "sprtElo0": 0
  },
  {
    "id": "6849a58fe84567164b5c9d81",
    "username": "sg",
    "branch": "tweak_more_lmr3",
    "llr": 0.4435314454666141,
    "wins": 25505,
    "losses": 25321,
    "draws": 48502,
    "workers": 3,
    "sprtElo0": 0
  },
  {
    "id": "6849d37ee84567164b5c9ec9",
    "username": "shawnxu",
    "branch": "test1461",
    "llr": 0.272047729668441,
    "wins": 47374,
    "losses": 47083,
    "draws": 88871,
    "workers": 6,
    "sprtElo0": 0
  },
  {
    "id": "68486106b1a2b107ef24f9b9",
    "username": "DanSamek",
    "branch": "tt_cap_cm_bonus_1",
    "llr": 0.20512129376309132,
    "wins": 62577,
    "losses": 62205,
    "draws": 117714,
    "workers": 6,
    "sprtElo0": 0
  },
  {
    "id": "684d1c78703522d4f129c93d",
    "username": "Vizvezdenec",
    "branch": "moreCtc2",
    "llr": 0.1375908229222055,
    "wins": 506,
    "losses": 491,
    "draws": 987,
    "workers": 3,
    "sprtElo0": 0
  },
  {
    "id": "68486253b1a2b107ef24f9bd",
    "username": "DanSamek",
    "branch": "tt_cap_cm_bonus_2",
    "llr": 0.09307169407088814,
    "wins": 104834,
    "losses": 104234,
    "draws": 196756,
    "workers": 3,
    "sprtElo0": 0
  },
  {
    "id": "684d3b00703522d4f129c949",
    "username": "DanSamek",
    "branch": "mc_bl",
    "llr": 0.02976454482031874,
    "wins": 418,
    "losses": 413,
    "draws": 801,
    "workers": 3,
    "sprtElo0": 0
  },
  {
    "id": "6848d841e84567164b5c9bdd",
    "username": "fauzi2",
    "branch": "ttag",
    "llr": 0,
    "wins": 0,
    "losses": 0,
    "draws": 0,
    "workers": 0,
    "sprtElo0": 0.5
  },
  {
    "id": "68459c9f375c2b77d98553c8",
    "username": "fauzi2",
    "branch": "cude",
    "llr": -0.029452893472993586,
    "wins": 186,
    "losses": 187,
    "draws": 317,
    "workers": 0,
    "sprtElo0": 0.5
  },
  {
    "id": "6845a0f7375c2b77d98553cc",
    "username": "fauzi2",
    "branch": "cude",
    "llr": -0.04983101739745474,
    "wins": 11010,
    "losses": 10934,
    "draws": 20786,
    "workers": 8,
    "sprtElo0": 0.5
  },
  {
    "id": "6844dfd41d7aa377ed9cef44",
    "username": "sg",
    "branch": "tweak_less_lmr4",
    "llr": -0.08366888514232741,
    "wins": 21962,
    "losses": 21845,
    "draws": 41409,
    "workers": 3,
    "sprtElo0": 0
  },
  {
    "id": "684c1ea1703522d4f129c5b9",
    "username": "Nonlinear",
    "branch": "smallnet-cv",
    "llr": -0.10774055056773336,
    "wins": 8442,
    "losses": 8404,
    "draws": 15954,
    "workers": 3,
    "sprtElo0": 0
  },
  {
    "id": "684c55aa703522d4f129c5ee",
    "username": "ergodice",
    "branch": "quietstreaksimp1",
    "llr": -0.1303433405963622,
    "wins": 4582,
    "losses": 4613,
    "draws": 8629,
    "workers": 4,
    "sprtElo0": -1.75
  },
  {
    "id": "684d1b66703522d4f129c939",
    "username": "Vizvezdenec",
    "branch": "incFixup1",
    "llr": -0.13545573310755654,
    "wins": 1017,
    "losses": 1023,
    "draws": 1928,
    "workers": 3,
    "sprtElo0": 0
  },
  {
    "id": "684638b6ce2583915b6b0448",
    "username": "sg",
    "branch": "tweak_less_lmr7",
    "llr": -0.14451948758306127,
    "wins": 50246,
    "losses": 49976,
    "draws": 94146,
    "workers": 3,
    "sprtElo0": 0
  },
  {
    "id": "684cce43703522d4f129c900",
    "username": "AliceRoselia",
    "branch": "fortress_detection",
    "llr": -0.21308014941086087,
    "wins": 5273,
    "losses": 5262,
    "draws": 9849,
    "workers": 3,
    "sprtElo0": 0
  },
  {
    "id": "684bd1f0703522d4f129c56b",
    "username": "snicolet",
    "branch": "mat2",
    "llr": -0.27255460125687037,
    "wins": 8977,
    "losses": 8950,
    "draws": 17145,
    "workers": 0,
    "sprtElo0": 0
  },
  {
    "id": "684d1bff703522d4f129c93b",
    "username": "Vizvezdenec",
    "branch": "moreCtc1",
    "llr": -0.467011485801546,
    "wins": 870,
    "losses": 906,
    "draws": 1680,
    "workers": 3,
    "sprtElo0": 0
  },
  {
    "id": "6849ab97e84567164b5c9ddf",
    "username": "Vizvezdenec",
    "branch": "cnAfterNmp8",
    "llr": -0.5042880075798664,
    "wins": 29809,
    "losses": 29685,
    "draws": 56346,
    "workers": 3,
    "sprtElo0": 0
  },
  {
    "id": "6849e994e84567164b5c9f21",
    "username": "0x539",
    "branch": "mp-pawns",
    "llr": -0.5057625351968454,
    "wins": 1282,
    "losses": 1319,
    "draws": 2487,
    "workers": 0,
    "sprtElo0": 0
  },
  {
    "id": "684c6ce9703522d4f129c602",
    "username": "ergodice",
    "branch": "an2",
    "llr": -0.5463830922955012,
    "wins": 5826,
    "losses": 5841,
    "draws": 11117,
    "workers": 4,
    "sprtElo0": 0
  },
  {
    "id": "68494cece84567164b5c9c4f",
    "username": "pb00067",
    "branch": "avoidSEEonKingMove",
    "llr": -0.6066873749666412,
    "wins": 32935,
    "losses": 32809,
    "draws": 61968,
    "workers": 0,
    "sprtElo0": 0
  },
  {
    "id": "684ad814e84567164b5ca069",
    "username": "sg",
    "branch": "tweak_more_lmr4",
    "llr": -0.709630331915314,
    "wins": 7739,
    "losses": 7758,
    "draws": 14327,
    "workers": 0,
    "sprtElo0": 0
  },
  {
    "id": "68456861375c2b77d9855360",
    "username": "sg",
    "branch": "tweak_less_lmr6",
    "llr": -0.7354692154209317,
    "wins": 32254,
    "losses": 32136,
    "draws": 60890,
    "workers": 0,
    "sprtElo0": 0
  },
  {
    "id": "68475e5d80918a66caa2eec2",
    "username": "sg",
    "branch": "tweak_less_lmr8",
    "llr": -0.8387884279433894,
    "wins": 32905,
    "losses": 32794,
    "draws": 61373,
    "workers": 0,
    "sprtElo0": 0
  },
  {
    "id": "684a8bcde84567164b5ca002",
    "username": "pb00067",
    "branch": "mpDeliverLegal3",
    "llr": -0.9502545151097501,
    "wins": 35136,
    "losses": 35360,
    "draws": 66624,
    "workers": 5,
    "sprtElo0": -1.75
  },
  {
    "id": "684c1b8c703522d4f129c5b5",
    "username": "Nonlinear",
    "branch": "check-static-eval-3",
    "llr": -0.9574283912514981,
    "wins": 7633,
    "losses": 7674,
    "draws": 14357,
    "workers": 2,
    "sprtElo0": 0
  },
  {
    "id": "6844d12e1d7aa377ed9cef24",
    "username": "sg",
    "branch": "tweak_less_lmr3",
    "llr": -1.0513746614532948,
    "wins": 6106,
    "losses": 6163,
    "draws": 11571,
    "workers": 0,
    "sprtElo0": 0
  },
  {
    "id": "6849e082e84567164b5c9f10",
    "username": "Nonlinear",
    "branch": "tt-next-hist",
    "llr": -1.134254955482928,
    "wins": 14253,
    "losses": 14232,
    "draws": 27555,
    "workers": 6,
    "sprtElo0": 0.5
  },
  {
    "id": "68491b77e84567164b5c9c0c",
    "username": "ergodice",
    "branch": "an1",
    "llr": -1.248870925993211,
    "wins": 38305,
    "losses": 38198,
    "draws": 72393,
    "workers": 3,
    "sprtElo0": 0
  },
  {
    "id": "684bd228703522d4f129c570",
    "username": "pb00067",
    "branch": "aspfailHigh",
    "llr": -1.2829933699244347,
    "wins": 15176,
    "losses": 15202,
    "draws": 29078,
    "workers": 5,
    "sprtElo0": 0
  },
  {
    "id": "684c8a5f703522d4f129c752",
    "username": "fauzi2",
    "branch": "ttag2",
    "llr": -1.3075565027784708,
    "wins": 5651,
    "losses": 5790,
    "draws": 10991,
    "workers": 3,
    "sprtElo0": -1.75
  },
  {
    "id": "6845301f1d7aa377ed9cf128",
    "username": "sg",
    "branch": "tweak_less_lmr5",
    "llr": -1.3567972637102437,
    "wins": 47661,
    "losses": 47509,
    "draws": 90718,
    "workers": 0,
    "sprtElo0": 0
  },
  {
    "id": "684b80af703522d4f129c50f",
    "username": "shawnxu",
    "branch": "test1464",
    "llr": -1.4107656551345067,
    "wins": 18911,
    "losses": 18927,
    "draws": 36018,
    "workers": 5,
    "sprtElo0": 0
  },
  {
    "id": "684bd1ae703522d4f129c569",
    "username": "snicolet",
    "branch": "mat2",
    "llr": -1.4354840419558683,
    "wins": 8046,
    "losses": 8126,
    "draws": 15508,
    "workers": 0,
    "sprtElo0": 0
  },
  {
    "id": "68493701e84567164b5c9c33",
    "username": "pb00067",
    "branch": "mpDeliverLegal",
    "llr": -1.5512765526773382,
    "wins": 19000,
    "losses": 19207,
    "draws": 36161,
    "workers": 0,
    "sprtElo0": -1.75
  },
  {
    "id": "68469c59ce2583915b6b04a4",
    "username": "Fisherman",
    "branch": "QSTweak",
    "llr": -1.6003032854001076,
    "wins": 48088,
    "losses": 47837,
    "draws": 92139,
    "workers": 5,
    "sprtElo0": 0.5
  },
  {
    "id": "6841e632b3a7bbdcda9a4527",
    "username": "sg",
    "branch": "tweak_more_lmr",
    "llr": -1.6381960213731708,
    "wins": 48122,
    "losses": 47995,
    "draws": 90667,
    "workers": 0,
    "sprtElo0": 0
  },
  {
    "id": "684c58d6703522d4f129c5fb",
    "username": "ergodice",
    "branch": "unctune3",
    "llr": -1.7633364030607992,
    "wins": 6566,
    "losses": 6683,
    "draws": 12447,
    "workers": 3,
    "sprtElo0": 0
  },
  {
    "id": "684690ebce2583915b6b0498",
    "username": "Fisherman",
    "branch": "QSTweak",
    "llr": -1.829635573201822,
    "wins": 48818,
    "losses": 48578,
    "draws": 94178,
    "workers": 6,
    "sprtElo0": 0.5
  },
  {
    "id": "6847386e80918a66caa2ee91",
    "username": "Vizvezdenec",
    "branch": "cnAfterNmp5",
    "llr": -1.8675626285147036,
    "wins": 63358,
    "losses": 63166,
    "draws": 118692,
    "workers": 4,
    "sprtElo0": 0
  },
  {
    "id": "684bd34f703522d4f129c578",
    "username": "sg",
    "branch": "lmr_ttcap",
    "llr": -1.8818457518296834,
    "wins": 9594,
    "losses": 9705,
    "draws": 18141,
    "workers": 4,
    "sprtElo0": 0
  },
  {
    "id": "684b1d4ce84567164b5ca0ae",
    "username": "sg",
    "branch": "tweak_more_lmr5",
    "llr": -1.8830656890047426,
    "wins": 5552,
    "losses": 5686,
    "draws": 10682,
    "workers": 0,
    "sprtElo0": 0
  },
  {
    "id": "68442627b13ab72e4642210a",
    "username": "Nonlinear",
    "branch": "tt-next-hist",
    "llr": -1.9784737712234077,
    "wins": 103979,
    "losses": 103566,
    "draws": 196647,
    "workers": 4,
    "sprtElo0": 0
  },
  {
    "id": "683bb8476ec7634154f9d866",
    "username": "0x539",
    "branch": "score-king2",
    "llr": -2.203963590186707,
    "wins": 31387,
    "losses": 31403,
    "draws": 59290,
    "workers": 0,
    "sprtElo0": 0
  },
  {
    "id": "684a1822e84567164b5c9f6e",
    "username": "ergodice",
    "branch": "unctmp",
    "llr": null,
    "wins": 22760,
    "losses": 22880,
    "draws": 42638,
    "workers": 4,
    "sprtElo0": null
  }
]